README.rst
setup.cfg
setup.py
boardgamegeek/__init__.py
boardgamegeek/api.py
boardgamegeek/collection.py
boardgamegeek/exceptions.py
boardgamegeek/games.py
boardgamegeek/guild.py
boardgamegeek/hotitems.py
boardgamegeek/main.py
boardgamegeek/plays.py
boardgamegeek/search.py
boardgamegeek/things.py
boardgamegeek/user.py
boardgamegeek/utils.py
boardgamegeek/version.py
boardgamegeek.egg-info/PKG-INFO
boardgamegeek.egg-info/SOURCES.txt
boardgamegeek.egg-info/dependency_links.txt
boardgamegeek.egg-info/entry_points.txt
boardgamegeek.egg-info/requires.txt
boardgamegeek.egg-info/top_level.txt
test/test_bgg.py